polyglot_bridge/__init__.py
polyglot_bridge/__init__.pyi
polyglot_bridge/polyglot_bridge.cpython-311-x86_64-linux-gnu.so
polyglot_bridge/py.typed
polyglot_bridge-0.2.0.dist-info/METADATA
polyglot_bridge-0.2.0.dist-info/WHEEL
polyglot_bridge-0.2.0.dist-info/RECORD
