Metadata-Version: 2.4
Name: polyglot-bridge
Version: 0.2.0
Classifier: Development Status :: 4 - Beta
Classifier: Intended Audience :: Developers
Classifier: Intended Audience :: Science/Research
Classifier: License :: OSI Approved :: MIT License
Classifier: Programming Language :: Rust
Classifier: Programming Language :: Python :: 3.8
Classifier: Programming Language :: Python :: 3.9
Classifier: Programming Language :: Python :: 3.10
Classifier: Programming Language :: Python :: 3.11
Classifier: Programming Language :: Python :: 3.12
Classifier: Programming Language :: Python :: 3.13
Classifier: Programming Language :: Python :: 3.14
Classifier: Topic :: Scientific/Engineering
Classifier: Topic :: Software Development :: Libraries
Summary: High-performance ML data pipeline accelerator - Rust-powered computational functions with seamless Python integration
Keywords: rust,python,performance,ml,data-pipeline,pyo3,ffi
Author-email: Septian Faturohman <farizseptian24@gmail.com>
License: MIT
Requires-Python: >=3.8
Project-URL: Documentation, https://github.com/nirvagold/polyglot-bridge#readme
Project-URL: Homepage, https://github.com/nirvagold/polyglot-bridge
Project-URL: Issues, https://github.com/nirvagold/polyglot-bridge/issues
Project-URL: Repository, https://github.com/nirvagold/polyglot-bridge
